{
    "numTotalResults": 1841,
    "numFilteredResults": 25,
    "numFilteredLearningResults": 25,
    "numStoredItems": 1841,
    "results": [
        {
            "id": 117306780,
            "userID": 13505514,
            "hash": "cd73b66617b8ac5838a7e27f7d093934",
            "srcText": "bottle",
            "trgText": "fles",
            "srcContext": "",
            "trgContext": "",
            "srcLang": "en",
            "trgLang": "nl",
            "srcPos": null,
            "trgPos": null,
            "creationDate": "2026-06-12T15:09:14Z",
            "removed": false,
            "comment": " flesje,  flacon",
            "domain": null,
            "document": "",
            "source": 1,
            "documentTitle": "",
            "register": null,
            "languageLevel": null,
            "trgTextEdited": null,
            "srcSegment": "",
            "historyID": null,
            "lastEdit": "2026-06-12T15:09:14Z",
            "favType": null,
            "lists": [],
            "learnCard": {
                "id": 13594237,
                "lastSeenDate": "2026-06-12T15:33:29Z",
                "timesSeen": 0,
                "srsCounter": 0,
                "status": "NOT_STARTED"
            }
        },
        {
            "id": 117309411,
            "userID": 13505514,
            "hash": "5738cc21177edcb3340f37b2b14c9ce2",
            "srcText": "bottle",
            "trgText": "fles",
            "srcContext": "<em>bottle</em>",
            "trgContext": "<em>fles</em>",
            "srcLang": "en",
            "trgLang": "nl",
            "srcPos": null,
            "trgPos": null,
            "creationDate": "2026-06-12T15:09:13Z",
            "removed": false,
            "comment": " flesje,  flacon",
            "domain": null,
            "document": "",
            "source": 1,
            "documentTitle": "",
            "register": null,
            "languageLevel": null,
            "trgTextEdited": "fles",
            "srcSegment": "",
            "historyID": null,
            "lastEdit": "2026-06-12T15:26:57Z",
            "favType": null,
            "lists": [],
            "learnCard": {
                "id": 13594237,
                "lastSeenDate": "2026-06-12T15:33:29Z",
                "timesSeen": 0,
                "srsCounter": 0,
                "status": "NOT_STARTED"
            }
        },
        {
            "id": 117306779,
            "userID": 13505514,
            "hash": "88298ac4145f6be5f804e33c78575823",
            "srcText": "table",
            "trgText": "tafel",
            "srcContext": "",
            "trgContext": "",
            "srcLang": "en",
            "trgLang": "nl",
            "srcPos": null,
            "trgPos": null,
            "creationDate": "2026-06-12T15:09:13Z",
            "removed": false,
            "comment": " tabel,  tafeltje",
            "domain": null,
            "document": "",
            "source": 1,
            "documentTitle": "",
            "register": null,
            "languageLevel": null,
            "trgTextEdited": null,
            "srcSegment": "",
            "historyID": null,
            "lastEdit": "2026-06-12T15:09:13Z",
            "favType": null,
            "lists": [],
            "learnCard": {
                "id": 13594238,
                "lastSeenDate": "2026-06-12T15:33:30Z",
                "timesSeen": 0,
                "srsCounter": 0,
                "status": "NOT_STARTED"
            }
        },
        {
            "id": 117309410,
            "userID": 13505514,
            "hash": "3c6c8484dfd570ad4939befbc6c9abea",
            "srcText": "table",
            "trgText": "tafel",
            "srcContext": "<em>table</em>",
            "trgContext": "<em>tafel</em>",
            "srcLang": "en",
            "trgLang": "nl",
            "srcPos": null,
            "trgPos": null,
            "creationDate": "2026-06-12T15:09:12Z",
            "removed": false,
            "comment": " tabel,  tafeltje",
            "domain": null,
            "document": "",
            "source": 1,
            "documentTitle": "",
            "register": null,
            "languageLevel": null,
            "trgTextEdited": "tafel",
            "srcSegment": "",
            "historyID": null,
            "lastEdit": "2026-06-12T15:26:57Z",
            "favType": null,
            "lists": [],
            "learnCard": {
                "id": 13594238,
                "lastSeenDate": "2026-06-12T15:33:30Z",
                "timesSeen": 0,
                "srsCounter": 0,
                "status": "NOT_STARTED"
            }
        },
        {
            "id": 117306776,
            "userID": 13505514,
            "hash": "1ccae4a58a69cdb3c5d7045d2be2b06e",
            "srcText": "computer",
            "trgText": "computer",
            "srcContext": "",
            "trgContext": "",
            "srcLang": "en",
            "trgLang": "nl",
            "srcPos": null,
            "trgPos": null,
            "creationDate": "2026-06-12T15:09:12Z",
            "removed": false,
            "comment": " pc,  laptop",
            "domain": null,
            "document": "",
            "source": 1,
            "documentTitle": "",
            "register": null,
            "languageLevel": null,
            "trgTextEdited": null,
            "srcSegment": "",
            "historyID": null,
            "lastEdit": "2026-06-12T15:09:12Z",
            "favType": null,
            "lists": [],
            "learnCard": {
                "id": 13594239,
                "lastSeenDate": "2026-06-12T15:33:30Z",
                "timesSeen": 0,
                "srsCounter": 0,
                "status": "NOT_STARTED"
            }
        },
        {
            "id": 117309409,
            "userID": 13505514,
            "hash": "d3e34fc236528aa17dba1cc11dddbb6e",
            "srcText": "computer",
            "trgText": "computer",
            "srcContext": "<em>computer</em>",
            "trgContext": "<em>computer</em>",
            "srcLang": "en",
            "trgLang": "nl",
            "srcPos": null,
            "trgPos": null,
            "creationDate": "2026-06-12T15:09:11Z",
            "removed": false,
            "comment": " pc,  laptop",
            "domain": null,
            "document": "",
            "source": 1,
            "documentTitle": "",
            "register": null,
            "languageLevel": null,
            "trgTextEdited": "computer",
            "srcSegment": "",
            "historyID": null,
            "lastEdit": "2026-06-12T15:26:57Z",
            "favType": null,
            "lists": [],
            "learnCard": {
                "id": 13594239,
                "lastSeenDate": "2026-06-12T15:33:30Z",
                "timesSeen": 0,
                "srsCounter": 0,
                "status": "NOT_STARTED"
            }
        },
        {
            "id": 117306775,
            "userID": 13505514,
            "hash": "676aab9a0b8cd692f85e67548c364a84",
            "srcText": "building",
            "trgText": "gebouw",
            "srcContext": "",
            "trgContext": "",
            "srcLang": "en",
            "trgLang": "nl",
            "srcPos": null,
            "trgPos": null,
            "creationDate": "2026-06-12T15:09:11Z",
            "removed": false,
            "comment": " bouwen,  pand",
            "domain": null,
            "document": "",
            "source": 1,
            "documentTitle": "",
            "register": null,
            "languageLevel": null,
            "trgTextEdited": null,
            "srcSegment": "",
            "historyID": null,
            "lastEdit": "2026-06-12T15:09:11Z",
            "favType": null,
            "lists": [],
            "learnCard": {
                "id": 13594240,
                "lastSeenDate": "2026-06-12T15:33:30Z",
                "timesSeen": 0,
                "srsCounter": 0,
                "status": "NOT_STARTED"
            }
        },
        {
            "id": 117306774,
            "userID": 13505514,
            "hash": "ec9f610b63b4686cb89b27ff51c968fe",
            "srcText": "past",
            "trgText": "verleden",
            "srcContext": "",
            "trgContext": "",
            "srcLang": "en",
            "trgLang": "nl",
            "srcPos": null,
            "trgPos": null,
            "creationDate": "2026-06-12T15:09:11Z",
            "removed": false,
            "comment": " afgelopen,  vroeger",
            "domain": null,
            "document": "",
            "source": 1,
            "documentTitle": "",
            "register": null,
            "languageLevel": null,
            "trgTextEdited": null,
            "srcSegment": "",
            "historyID": null,
            "lastEdit": "2026-06-12T15:09:11Z",
            "favType": null,
            "lists": [],
            "learnCard": {
                "id": 13594241,
                "lastSeenDate": "2026-06-12T15:33:31Z",
                "timesSeen": 0,
                "srsCounter": 0,
                "status": "NOT_STARTED"
            }
        },
        {
            "id": 117309408,
            "userID": 13505514,
            "hash": "8aa8cd3eb4c1bbf1699d84f33ad31a4d",
            "srcText": "building",
            "trgText": "gebouw",
            "srcContext": "<em>building</em>",
            "trgContext": "<em>gebouw</em>",
            "srcLang": "en",
            "trgLang": "nl",
            "srcPos": null,
            "trgPos": null,
            "creationDate": "2026-06-12T15:09:10Z",
            "removed": false,
            "comment": " bouwen,  pand",
            "domain": null,
            "document": "",
            "source": 1,
            "documentTitle": "",
            "register": null,
            "languageLevel": null,
            "trgTextEdited": "gebouw",
            "srcSegment": "",
            "historyID": null,
            "lastEdit": "2026-06-12T15:26:57Z",
            "favType": null,
            "lists": [],
            "learnCard": {
                "id": 13594240,
                "lastSeenDate": "2026-06-12T15:33:30Z",
                "timesSeen": 0,
                "srsCounter": 0,
                "status": "NOT_STARTED"
            }
        },
        {
            "id": 117309407,
            "userID": 13505514,
            "hash": "8f74752b101e7e7052138ea308627298",
            "srcText": "past",
            "trgText": "verleden",
            "srcContext": "<em>past</em>",
            "trgContext": "<em>verleden</em>",
            "srcLang": "en",
            "trgLang": "nl",
            "srcPos": null,
            "trgPos": null,
            "creationDate": "2026-06-12T15:09:10Z",
            "removed": false,
            "comment": " afgelopen,  vroeger",
            "domain": null,
            "document": "",
            "source": 1,
            "documentTitle": "",
            "register": null,
            "languageLevel": null,
            "trgTextEdited": "verleden",
            "srcSegment": "",
            "historyID": null,
            "lastEdit": "2026-06-12T15:26:57Z",
            "favType": null,
            "lists": [],
            "learnCard": {
                "id": 13594241,
                "lastSeenDate": "2026-06-12T15:33:31Z",
                "timesSeen": 0,
                "srsCounter": 0,
                "status": "NOT_STARTED"
            }
        },
        {
            "id": 117306773,
            "userID": 13505514,
            "hash": "66d77cf76a7848db30fdf601489f54b6",
            "srcText": "basic",
            "trgText": "fundamenteel",
            "srcContext": "",
            "trgContext": "",
            "srcLang": "en",
            "trgLang": "nl",
            "srcPos": null,
            "trgPos": null,
            "creationDate": "2026-06-12T15:09:10Z",
            "removed": false,
            "comment": " eenvoudig,  basaal",
            "domain": null,
            "document": "",
            "source": 1,
            "documentTitle": "",
            "register": null,
            "languageLevel": null,
            "trgTextEdited": null,
            "srcSegment": "",
            "historyID": null,
            "lastEdit": "2026-06-12T15:09:10Z",
            "favType": null,
            "lists": [],
            "learnCard": {
                "id": 13594242,
                "lastSeenDate": "2026-06-12T15:33:31Z",
                "timesSeen": 0,
                "srsCounter": 0,
                "status": "NOT_STARTED"
            }
        },
        {
            "id": 117309406,
            "userID": 13505514,
            "hash": "b5d93f84e543d6054a9d3de8c1b23229",
            "srcText": "basic",
            "trgText": "fundamenteel",
            "srcContext": "<em>basic</em>",
            "trgContext": "<em>fundamenteel</em>",
            "srcLang": "en",
            "trgLang": "nl",
            "srcPos": null,
            "trgPos": null,
            "creationDate": "2026-06-12T15:09:09Z",
            "removed": false,
            "comment": " eenvoudig,  basaal",
            "domain": null,
            "document": "",
            "source": 1,
            "documentTitle": "",
            "register": null,
            "languageLevel": null,
            "trgTextEdited": "fundamenteel",
            "srcSegment": "",
            "historyID": null,
            "lastEdit": "2026-06-12T15:26:57Z",
            "favType": null,
            "lists": [],
            "learnCard": {
                "id": 13594242,
                "lastSeenDate": "2026-06-12T15:33:31Z",
                "timesSeen": 0,
                "srsCounter": 0,
                "status": "NOT_STARTED"
            }
        },
        {
            "id": 117306748,
            "userID": 13505514,
            "hash": "4f91e3b01861b4eb05708bf8d2d625c9",
            "srcText": "basic",
            "trgText": "fundamentele",
            "srcContext": "Families represent the most <em>basic</em> social unit within our society.",
            "trgContext": "Gezinnen vormen de meest <em>fundamentele</em> sociale eenheid in onze samenleving.",
            "srcLang": "en",
            "trgLang": "nl",
            "srcPos": null,
            "trgPos": null,
            "creationDate": "2026-06-12T15:08:24Z",
            "removed": false,
            "comment": "",
            "domain": null,
            "document": "",
            "source": 0,
            "documentTitle": "",
            "register": null,
            "languageLevel": null,
            "trgTextEdited": null,
            "srcSegment": "",
            "historyID": null,
            "lastEdit": "2026-06-12T15:08:24Z",
            "favType": null,
            "lists": [],
            "learnCard": {
                "id": 13594243,
                "lastSeenDate": "2026-06-12T15:33:31Z",
                "timesSeen": 0,
                "srsCounter": 0,
                "status": "NOT_STARTED"
            }
        },
        {
            "id": 117306743,
            "userID": 13505514,
            "hash": "616e898d5d18d0c60518f508dedf16ef",
            "srcText": "past",
            "trgText": "verleden",
            "srcContext": "Many traditions have roots that trace back to the remote <em>past</em>.",
            "trgContext": "Veel tradities hebben wortels die teruggaan tot in een ver <em>verleden</em>.",
            "srcLang": "en",
            "trgLang": "nl",
            "srcPos": null,
            "trgPos": null,
            "creationDate": "2026-06-12T15:08:18Z",
            "removed": false,
            "comment": "",
            "domain": null,
            "document": "",
            "source": 0,
            "documentTitle": "",
            "register": null,
            "languageLevel": null,
            "trgTextEdited": null,
            "srcSegment": "",
            "historyID": null,
            "lastEdit": "2026-06-12T15:08:18Z",
            "favType": null,
            "lists": [],
            "learnCard": {
                "id": 13594241,
                "lastSeenDate": "2026-06-12T15:33:31Z",
                "timesSeen": 0,
                "srsCounter": 0,
                "status": "NOT_STARTED"
            }
        },
        {
            "id": 117306736,
            "userID": 13505514,
            "hash": "799cb9db7610fa2f16bd029349d92dc1",
            "srcText": "building",
            "trgText": "gebouw",
            "srcContext": "The leaking gas pipe caused alarm in the entire <em>building</em> promptly.",
            "trgContext": "De lekkende gasleiding zorgde meteen voor paniek in het hele <em>gebouw</em>.",
            "srcLang": "en",
            "trgLang": "nl",
            "srcPos": null,
            "trgPos": null,
            "creationDate": "2026-06-12T15:08:13Z",
            "removed": false,
            "comment": "",
            "domain": null,
            "document": "",
            "source": 0,
            "documentTitle": "",
            "register": null,
            "languageLevel": null,
            "trgTextEdited": null,
            "srcSegment": "",
            "historyID": null,
            "lastEdit": "2026-06-12T15:08:13Z",
            "favType": null,
            "lists": [],
            "learnCard": {
                "id": 13594240,
                "lastSeenDate": "2026-06-12T15:33:30Z",
                "timesSeen": 0,
                "srsCounter": 0,
                "status": "NOT_STARTED"
            }
        },
        {
            "id": 117306729,
            "userID": 13505514,
            "hash": "cc9c2f0cb3a31a35bc3369735aabd3af",
            "srcText": "computer",
            "trgText": "computer",
            "srcContext": "John was steaming when his <em>computer</em> crashed right before the deadline.",
            "trgContext": "John was laaiend toen zijn <em>computer</em> vastliep vlak voor de deadline.",
            "srcLang": "en",
            "trgLang": "nl",
            "srcPos": null,
            "trgPos": null,
            "creationDate": "2026-06-12T15:08:07Z",
            "removed": false,
            "comment": "",
            "domain": null,
            "document": "",
            "source": 0,
            "documentTitle": "",
            "register": null,
            "languageLevel": null,
            "trgTextEdited": null,
            "srcSegment": "",
            "historyID": null,
            "lastEdit": "2026-06-12T15:08:07Z",
            "favType": null,
            "lists": [],
            "learnCard": {
                "id": 13594239,
                "lastSeenDate": "2026-06-12T15:33:30Z",
                "timesSeen": 0,
                "srsCounter": 0,
                "status": "NOT_STARTED"
            }
        },
        {
            "id": 117306720,
            "userID": 13505514,
            "hash": "2dcb4347b3fbc65407ee566de98c49b3",
            "srcText": "bottle",
            "trgText": "fles",
            "srcContext": "He poured a foaming drink from the <em>bottle</em> into the glass.",
            "trgContext": "Hij schonk een schuimende drank uit de <em>fles</em> in het glas.",
            "srcLang": "en",
            "trgLang": "nl",
            "srcPos": null,
            "trgPos": null,
            "creationDate": "2026-06-12T15:08:02Z",
            "removed": false,
            "comment": "",
            "domain": null,
            "document": "",
            "source": 0,
            "documentTitle": "",
            "register": null,
            "languageLevel": null,
            "trgTextEdited": null,
            "srcSegment": "",
            "historyID": null,
            "lastEdit": "2026-06-12T15:08:02Z",
            "favType": null,
            "lists": [],
            "learnCard": {
                "id": 13594237,
                "lastSeenDate": "2026-06-12T15:33:29Z",
                "timesSeen": 0,
                "srsCounter": 0,
                "status": "NOT_STARTED"
            }
        },
        {
            "id": 117306715,
            "userID": 13505514,
            "hash": "11488209dafea42f776ce3740af72fd4",
            "srcText": "table",
            "trgText": "tafel",
            "srcContext": "A crackled texture covered the surface of the old wooden <em>table</em>.",
            "trgContext": "Een craquelé textuur bedekte het oppervlak van de oude houten <em>tafel</em>.",
            "srcLang": "en",
            "trgLang": "nl",
            "srcPos": null,
            "trgPos": null,
            "creationDate": "2026-06-12T15:07:57Z",
            "removed": false,
            "comment": "",
            "domain": null,
            "document": "",
            "source": 0,
            "documentTitle": "",
            "register": null,
            "languageLevel": null,
            "trgTextEdited": null,
            "srcSegment": "",
            "historyID": null,
            "lastEdit": "2026-06-12T15:07:57Z",
            "favType": null,
            "lists": [],
            "learnCard": {
                "id": 13594238,
                "lastSeenDate": "2026-06-12T15:33:30Z",
                "timesSeen": 0,
                "srsCounter": 0,
                "status": "NOT_STARTED"
            }
        },
        {
            "id": 117306699,
            "userID": 13505514,
            "hash": "503337f57de051cb9727d76e27cc942e",
            "srcText": "cloud",
            "trgText": "wolk",
            "srcContext": "",
            "trgContext": "",
            "srcLang": "en",
            "trgLang": "nl",
            "srcPos": null,
            "trgPos": null,
            "creationDate": "2026-06-12T15:07:30Z",
            "removed": false,
            "comment": " wolkje,  nevel",
            "domain": null,
            "document": "",
            "source": 1,
            "documentTitle": "",
            "register": null,
            "languageLevel": null,
            "trgTextEdited": null,
            "srcSegment": "",
            "historyID": null,
            "lastEdit": "2026-06-12T15:07:30Z",
            "favType": null,
            "lists": [],
            "learnCard": {
                "id": 13595086,
                "lastSeenDate": "2026-06-12T16:02:25Z",
                "timesSeen": 0,
                "srsCounter": 0,
                "status": "NOT_STARTED"
            }
        },
        {
            "id": 117309405,
            "userID": 13505514,
            "hash": "d6ab97848eb98c4f6348448c340d0f3a",
            "srcText": "cloud",
            "trgText": "wolk",
            "srcContext": "<em>cloud</em>",
            "trgContext": "<em>wolk</em>",
            "srcLang": "en",
            "trgLang": "nl",
            "srcPos": null,
            "trgPos": null,
            "creationDate": "2026-06-12T15:07:29Z",
            "removed": false,
            "comment": " wolkje,  nevel",
            "domain": null,
            "document": "",
            "source": 1,
            "documentTitle": "",
            "register": null,
            "languageLevel": null,
            "trgTextEdited": "wolk",
            "srcSegment": "",
            "historyID": null,
            "lastEdit": "2026-06-12T15:26:57Z",
            "favType": null,
            "lists": [],
            "learnCard": {
                "id": 13595086,
                "lastSeenDate": "2026-06-12T16:02:25Z",
                "timesSeen": 0,
                "srsCounter": 0,
                "status": "NOT_STARTED"
            }
        },
        {
            "id": 117306698,
            "userID": 13505514,
            "hash": "7590b177b19136c9f1f1a6e1d1d46232",
            "srcText": "fork",
            "trgText": "vork",
            "srcContext": "",
            "trgContext": "",
            "srcLang": "en",
            "trgLang": "nl",
            "srcPos": null,
            "trgPos": null,
            "creationDate": "2026-06-12T15:07:29Z",
            "removed": false,
            "comment": " voorvork,  fork",
            "domain": null,
            "document": "",
            "source": 1,
            "documentTitle": "",
            "register": null,
            "languageLevel": null,
            "trgTextEdited": null,
            "srcSegment": "",
            "historyID": null,
            "lastEdit": "2026-06-12T15:07:29Z",
            "favType": null,
            "lists": [],
            "learnCard": {
                "id": 13595085,
                "lastSeenDate": "2026-06-12T16:02:25Z",
                "timesSeen": 0,
                "srsCounter": 0,
                "status": "IGNORED"
            }
        },
        {
            "id": 117309404,
            "userID": 13505514,
            "hash": "a51d6712cd41afee14a31b5741f2637c",
            "srcText": "fork",
            "trgText": "vork",
            "srcContext": "<em>fork</em>",
            "trgContext": "<em>vork</em>",
            "srcLang": "en",
            "trgLang": "nl",
            "srcPos": null,
            "trgPos": null,
            "creationDate": "2026-06-12T15:07:28Z",
            "removed": false,
            "comment": " voorvork,  fork",
            "domain": null,
            "document": "",
            "source": 1,
            "documentTitle": "",
            "register": null,
            "languageLevel": null,
            "trgTextEdited": "vork",
            "srcSegment": "",
            "historyID": null,
            "lastEdit": "2026-06-12T15:26:57Z",
            "favType": null,
            "lists": [],
            "learnCard": {
                "id": 13595085,
                "lastSeenDate": "2026-06-12T16:02:25Z",
                "timesSeen": 0,
                "srsCounter": 0,
                "status": "IGNORED"
            }
        },
        {
            "id": 117306660,
            "userID": 13505514,
            "hash": "8b9191d055c32a2557e7be37b0dcceba",
            "srcText": "fork",
            "trgText": "vork",
            "srcContext": "The restaurant provided a knife and <em>fork</em> with every meal served.",
            "trgContext": "Het restaurant legde bij iedere maaltijd een mes en <em>vork</em> neer.",
            "srcLang": "en",
            "trgLang": "nl",
            "srcPos": null,
            "trgPos": null,
            "creationDate": "2026-06-12T15:07:00Z",
            "removed": false,
            "comment": "",
            "domain": null,
            "document": "",
            "source": 0,
            "documentTitle": "",
            "register": null,
            "languageLevel": null,
            "trgTextEdited": null,
            "srcSegment": "",
            "historyID": null,
            "lastEdit": "2026-06-12T15:07:00Z",
            "favType": null,
            "lists": [],
            "learnCard": {
                "id": 13595085,
                "lastSeenDate": "2026-06-12T16:02:25Z",
                "timesSeen": 0,
                "srsCounter": 0,
                "status": "IGNORED"
            }
        },
        {
            "id": 117306653,
            "userID": 13505514,
            "hash": "aff9b59fbf85527c8b41abd22d3da40a",
            "srcText": "cloud",
            "trgText": "wolk",
            "srcContext": "That fluffball looks like it just rolled out of a <em>cloud</em>.",
            "trgContext": "Die pluizenbol lijkt wel zo uit een <em>wolk</em> gerold te zijn.",
            "srcLang": "en",
            "trgLang": "nl",
            "srcPos": null,
            "trgPos": null,
            "creationDate": "2026-06-12T15:06:54Z",
            "removed": false,
            "comment": "",
            "domain": null,
            "document": "",
            "source": 0,
            "documentTitle": "",
            "register": null,
            "languageLevel": null,
            "trgTextEdited": null,
            "srcSegment": "",
            "historyID": null,
            "lastEdit": "2026-06-12T15:06:54Z",
            "favType": null,
            "lists": [],
            "learnCard": {
                "id": 13595086,
                "lastSeenDate": "2026-06-12T16:02:25Z",
                "timesSeen": 0,
                "srsCounter": 0,
                "status": "NOT_STARTED"
            }
        },
        {
            "id": 117292289,
            "userID": 13505514,
            "hash": "5f3c447bcefdef17d203455d049ee5f8",
            "srcText": "I want to translate a sentence",
            "trgText": "Ik wil een zin vertalen",
            "srcContext": "",
            "trgContext": "",
            "srcLang": "en",
            "trgLang": "nl",
            "srcPos": null,
            "trgPos": null,
            "creationDate": "2026-06-12T13:14:25Z",
            "removed": false,
            "comment": "",
            "domain": null,
            "document": "",
            "source": 0,
            "documentTitle": "",
            "register": null,
            "languageLevel": null,
            "trgTextEdited": null,
            "srcSegment": "",
            "historyID": null,
            "lastEdit": "2026-06-12T13:14:25Z",
            "favType": "",
            "lists": [],
            "learnCard": {
                "id": 13589769,
                "lastSeenDate": "2026-06-12T13:14:48Z",
                "timesSeen": 0,
                "srsCounter": 0,
                "status": "NOT_STARTED"
            }
        }
    ],
    "learningStatus": {
        "totalCards": 702,
        "totalCardsFiltered": 25,
        "memorizedOnceCards": 0,
        "memorizedOnceCardsFiltered": 0,
        "activeCards": 698,
        "activeCardsFiltered": 22,
        "ignoredCards": 4,
        "ignoredCardsFiltered": 3,
        "notStartedCards": 611,
        "notStartedCardsFiltered": 22,
        "inProgressCards": 87,
        "inProgressCardsFiltered": 0,
        "memoryScoreOnlyCards": 0.0347,
        "memoryScoreOnlyCardsFiltered": 0.0000,
        "memoryScore": 0.0132,
        "memoryScoreFiltered": 0.0000,
        "statsBySRSCounter": {
            "NOT_STARTED": 22
        },
        "totalItemsNotStarted": 1750,
        "totalFilteredItemsNotStarted": 22,
        "statsByLastStatus": {},
        "statsBySource": {
            "favourites": 19,
            "history": 3
        }
    },
    "count": {
        "en-nl": 25
    }
}